python/__init__.py
python/nicehash.py
python/test_bot.py
nicehash_python-0.0.1.dist-info/METADATA
nicehash_python-0.0.1.dist-info/WHEEL
nicehash_python-0.0.1.dist-info/entry_points.txt
nicehash_python-0.0.1.dist-info/top_level.txt
nicehash_python-0.0.1.dist-info/RECORD
