Metadata-Version: 2.1
Name: nicehash-python
Version: 0.0.1
Summary: NiceHash API
Home-page: https://github.com/skeetzo/nicehash-python
Author: Skeetzo
Author-email: WebmasterSkeetzo@gmail.com
License: UNKNOWN
Keywords: nicehash,api,python
Platform: UNKNOWN
Classifier: Development Status :: 5 - Production/Stable
Classifier: Environment :: Console
Classifier: Intended Audience :: Developers
Classifier: Topic :: Office/Business :: Financial :: Investment
Classifier: License :: OSI Approved :: MIT License
Classifier: Natural Language :: English
Classifier: Operating System :: POSIX :: Linux
Classifier: Programming Language :: Python :: 3
Classifier: Topic :: Software Development :: Libraries :: Python Modules
Requires-Dist: requests
Provides-Extra: dev
Requires-Dist: dotenv-python ; extra == 'dev'
